LICENSE
MANIFEST.in
README.md
setup.py
testingthingforpython/__init__.py
testingthingforpython/api_helper.py
testingthingforpython/configuration.py
testingthingforpython/decorators.py
testingthingforpython/testingthingforpython_client.py
testingthingforpython.egg-info/PKG-INFO
testingthingforpython.egg-info/SOURCES.txt
testingthingforpython.egg-info/dependency_links.txt
testingthingforpython.egg-info/requires.txt
testingthingforpython.egg-info/top_level.txt
testingthingforpython/controllers/__init__.py
testingthingforpython/controllers/api_controller.py
testingthingforpython/controllers/base_controller.py
testingthingforpython/exceptions/__init__.py
testingthingforpython/exceptions/api_exception.py
testingthingforpython/http/__init__.py
testingthingforpython/http/http_call_back.py
testingthingforpython/http/http_client.py
testingthingforpython/http/http_context.py
testingthingforpython/http/http_method_enum.py
testingthingforpython/http/http_request.py
testingthingforpython/http/http_response.py
testingthingforpython/http/requests_client.py
testingthingforpython/http/auth/__init__.py
testingthingforpython/http/auth/basic_auth.py
testingthingforpython/models/__init__.py
testingthingforpython/models/suite_code_enum.py
tests/__init__.py
tests/http_response_catcher.py
tests/test_helper.py
tests/controllers/__init__.py
tests/controllers/controller_test_base.py
tests/controllers/test_api_controller.py