Metadata-Version: 1.0
Name: testingthingforpython
Version: 1.1.0
Summary: TODO: add library description
Home-page: https://apimatic.io
Author: APIMatic SDK Generator
Author-email: support@apimatic.io
License: UNKNOWN
Platform: UNKNOWN
